LICENSE
MANIFEST.in
README.rst
setup.py
btc_fake_formset.egg-info/PKG-INFO
btc_fake_formset.egg-info/SOURCES.txt
btc_fake_formset.egg-info/dependency_links.txt
btc_fake_formset.egg-info/top_level.txt
fake_formset/__init__.py
fake_formset/apps.py
fake_formset/static/fake_formset/css/fake_formset.css
fake_formset/static/fake_formset/js/fake_formset.js