Metadata-Version: 1.1
Name: btc-fake-formset
Version: 0.1.1
Summary: Fake Formset designed to display data of one form field (separated by characters) as a set of fields.
Home-page: https://github.com/MEADez/btc-fake-formset
Author: MEADez
Author-email: m3adez@gmail.com
License: BSD License
Platform: UNKNOWN
Classifier: Environment :: Web Environment
Classifier: Framework :: Django
Classifier: Intended Audience :: Developers
Classifier: License :: OSI Approved :: BSD License
Classifier: Operating System :: OS Independent
Classifier: Programming Language :: Python :: 3.6
Classifier: Topic :: Internet :: WWW/HTTP
Classifier: Topic :: Internet :: WWW/HTTP :: Dynamic Content
